tokenc/__init__.py
tokenc/client.py
tokenc/constants.py
tokenc/errors.py
tokenc/types.py
tokenc-0.1.2.dist-info/licenses/LICENSE
tokenc-0.1.2.dist-info/METADATA
tokenc-0.1.2.dist-info/WHEEL
tokenc-0.1.2.dist-info/top_level.txt
tokenc-0.1.2.dist-info/RECORD
