Metadata-Version: 2.4
Name: tokenc
Version: 0.1.2
Summary: Python SDK for The Token Company API - Compress LLM inputs to reduce costs
Home-page: https://github.com/yourusername/tokenc
Author: The Token Company
Author-email: The Token Company <support@thetokencompany.com>
License: MIT
Project-URL: Homepage, https://thetokencompany.com
Project-URL: Documentation, https://thetokencompany.com/docs
Project-URL: Repository, https://github.com/yourusername/tokenc
Project-URL: Bug Tracker, https://github.com/yourusername/tokenc/issues
Keywords: llm,compression,tokens,ai,api,cost-optimization
Classifier: Development Status :: 3 - Alpha
Classifier: Intended Audience :: Developers
Classifier: Topic :: Software Development :: Libraries :: Python Modules
Classifier: License :: OSI Approved :: MIT License
Classifier: Programming Language :: Python :: 3
Classifier: Programming Language :: Python :: 3.7
Classifier: Programming Language :: Python :: 3.8
Classifier: Programming Language :: Python :: 3.9
Classifier: Programming Language :: Python :: 3.10
Classifier: Programming Language :: Python :: 3.11
Classifier: Programming Language :: Python :: 3.12
Requires-Python: >=3.7
License-File: LICENSE
Requires-Dist: requests>=2.25.0
Provides-Extra: dev
Requires-Dist: pytest>=7.0.0; extra == "dev"
Requires-Dist: pytest-cov>=3.0.0; extra == "dev"
Requires-Dist: black>=22.0.0; extra == "dev"
Requires-Dist: mypy>=0.950; extra == "dev"
Requires-Dist: flake8>=4.0.0; extra == "dev"
Dynamic: author
Dynamic: home-page
Dynamic: license-file
Dynamic: requires-python
